HitachiBlockAPI/Hitachi.py
HitachiBlockAPI/__init__.py
HitachiBlockAPI-0.9.2.dist-info/METADATA
HitachiBlockAPI-0.9.2.dist-info/WHEEL
HitachiBlockAPI-0.9.2.dist-info/top_level.txt
HitachiBlockAPI-0.9.2.dist-info/RECORD
