Metadata-Version: 2.1
Name: HitachiBlockAPI
Version: 0.9.2
Summary: Hitachi Storage REST API to ease the communication to Hitachi Storage
Home-page: https://github.com/pascalhubacher/HitachiStorageRestAPI
Author: Pascal Hubacher
License: UNKNOWN
Platform: UNKNOWN
Provides-Extra: full
Requires-Dist: wheel ; extra == 'full'
Requires-Dist: setuptools ; extra == 'full'
Requires-Dist: pytest ; extra == 'full'
Requires-Dist: pytest-html ; extra == 'full'
Requires-Dist: keyring ; extra == 'full'
Requires-Dist: twine ; extra == 'full'
Provides-Extra: minimal
